wiki_cli/__init__.py
wiki_cli/formatter.py
wiki_cli/models.py
wiki_cli/wiki.py
wiki_cli-0.4.1.dist-info/LICENSE
wiki_cli-0.4.1.dist-info/METADATA
wiki_cli-0.4.1.dist-info/WHEEL
wiki_cli-0.4.1.dist-info/entry_points.txt
wiki_cli-0.4.1.dist-info/RECORD
