Metadata-Version: 2.1
Name: wiki-cli
Version: 0.4.1
Summary: Command Line Client for quick lookups on Wikipedia.
Home-page: https://gitlab.com/sedrubal/wiki-cli.git
License: MIT
Author: sedrubal
Author-email: dev@sedrubal.de
Requires-Python: >=3.9,<4.0
Classifier: License :: OSI Approved :: MIT License
Classifier: Programming Language :: Python :: 3
Classifier: Programming Language :: Python :: 3.9
Classifier: Programming Language :: Python :: 3.10
Classifier: Programming Language :: Python :: 3.11
Requires-Dist: beautifulsoup4 (>=4.9.3,<5.0.0)
Requires-Dist: lxml (>=4.6.2,<5.0.0)
Requires-Dist: pre-commit (>=2.9.3,<3.0.0)
Requires-Dist: pyfzf (>=0.2.2,<0.3.0)
Requires-Dist: requests (>=2.25.0,<3.0.0)
Requires-Dist: termcolor (>=1.1.0,<2.0.0)
Project-URL: Repository, https://gitlab.com/sedrubal/wiki-cli.git
